{
   "gameId": "Fortnite",
   "eventId": "epicgames_S38_TouchOnlyMobileCup_EU",
   "beginTime": "2025-11-05T17:00:00Z",
   "endTime": "2025-11-05T21:15:00Z",
   "displayDataId": "s38_touchonly",
   "eventGroup": "Season38_TouchOnlyMobileCup",
   "announcementTime": "2025-08-07T07:00:00Z",
   "regions": [
      "EU"
   ],
   "regionMappings": {
      "EU": "EUCOMP"
   },
   "platforms": [
      "Android",
      "IOS"
   ],
   "platformMappings": {},
   "metadata": {
      "AccountLockType": "Window",
      "DisqualifyType": "Window",
      "minimumAccountLevel": 50,
      "webId": "S38_TouchOnlyMobileCup"
   },
   "eventWindows": [
      {
         "eventWindowId": "S38_TouchOnlyMobileCup_Final_EU",
         "eventTemplateId": "S38_TouchOnlyMobileCup_EventTemplate",
         "countdownBeginTime": "2025-08-31T18:00:00Z",
         "beginTime": "2025-11-05T20:00:00Z",
         "endTime": "2025-11-05T21:15:00Z",
         "round": 0,
         "payoutDelay": 20,
         "isTBD": false,
         "visibility": "public",
         "additionalRequirements": [
            "eula:s38_mobile_rules",
            "adps:g-a81a33a3b9a7",
            "mfa"
         ],
         "teammateEligibility": "all",
         "blackoutPeriods": [],
         "scoreLocations": [
            {
               "leaderboardDefId": "S38_TouchOnlyMobileCup_LeaderboardDef_Final",
               "isMainWindowLeaderboard": true
            }
         ],
         "canLiveSpectate": false,
         "requireAllTokens": [
            "S38_TouchOnlyMobileCup_Final_EU"
         ],
         "requireAnyTokens": [],
         "requireNoneTokensCaller": [
            "EpicAccountPrizingRestriction_v2",
            "Permanent_Tournament_Ban"
         ],
         "requireAllTokensCaller": [],
         "requireAnyTokensCaller": [],
         "regionMappings": {},
         "metadata": {
            "RoundType": "Qualifiers",
            "ScheduledMatchmakingInitialDelaySeconds": 300,
            "ScheduledMatchmakingMatchDelaySeconds": 420,
            "ServerReplays": true
         }
      },
      {
         "eventWindowId": "S38_TouchOnlyMobileCup_Round1_EU",
         "eventTemplateId": "S38_TouchOnlyMobileCup_EventTemplate",
         "countdownBeginTime": "2025-08-31T15:00:00Z",
         "beginTime": "2025-11-05T17:00:00Z",
         "endTime": "2025-11-05T18:00:00Z",
         "round": 0,
         "payoutDelay": 20,
         "isTBD": false,
         "visibility": "public",
         "additionalRequirements": [
            "eula:s38_mobile_rules",
            "adps:g-a81a33a3b9a7",
            "mfa",
            [
               "currentRanking:ranked-zb:6",
               "currentRanking:ranked-br:6",
               "currentRanking:ranked_blastberry_build:6",
               "currentRanking:ranked_blastberry_nobuild:6"
            ]
         ],
         "teammateEligibility": "all",
         "blackoutPeriods": [],
         "scoreLocations": [
            {
               "leaderboardDefId": "S38_TouchOnlyMobileCup_LeaderboardDef",
               "isMainWindowLeaderboard": true
            }
         ],
         "canLiveSpectate": false,
         "requireAllTokens": [],
         "requireAnyTokens": [],
         "requireNoneTokensCaller": [
            "EpicAccountPrizingRestriction_v2",
            "Permanent_Tournament_Ban"
         ],
         "requireAllTokensCaller": [],
         "requireAnyTokensCaller": [],
         "regionMappings": {},
         "metadata": {
            "RoundType": "Qualifiers",
            "ServerReplays": true
         }
      },
      {
         "eventWindowId": "S38_TouchOnlyMobileCup_Round2_EU",
         "eventTemplateId": "S38_TouchOnlyMobileCup_EventTemplate",
         "countdownBeginTime": "2025-08-31T16:30:00Z",
         "beginTime": "2025-11-05T18:30:00Z",
         "endTime": "2025-11-05T19:30:00Z",
         "round": 0,
         "payoutDelay": 20,
         "isTBD": false,
         "visibility": "public",
         "additionalRequirements": [
            "adps:g-a81a33a3b9a7",
            "input-touch",
            "mfa",
            "eula:s38_mobile_rules",
            [
               "currentRanking:ranked-zb:6",
               "currentRanking:ranked-br:6",
               "currentRanking:ranked_blastberry_build:6",
               "currentRanking:ranked_blastberry_nobuild:6"
            ]
         ],
         "teammateEligibility": "all",
         "blackoutPeriods": [],
         "scoreLocations": [
            {
               "leaderboardDefId": "S38_TouchOnlyMobileCup_LeaderboardDef",
               "isMainWindowLeaderboard": true
            }
         ],
         "canLiveSpectate": false,
         "requireAllTokens": [],
         "requireAnyTokens": [],
         "requireNoneTokensCaller": [
            "EpicAccountPrizingRestriction_v2",
            "Permanent_Tournament_Ban",
            "S38_TouchOnlyMobileCup_Final_EU"
         ],
         "requireAllTokensCaller": [],
         "requireAnyTokensCaller": [],
         "regionMappings": {},
         "metadata": {
            "RoundType": "Qualifiers",
            "ServerReplays": true
         }
      }
   ],
   "link": {
      "type": "br:tournament",
      "code": "tournament_epicgames_s38_touchonlymobilecup_eu"
   }
}