{
   "gameId": "Fortnite",
   "eventId": "epicgames_S37_BlitzCups_NAW",
   "beginTime": "2025-08-23T00:00:00Z",
   "endTime": "2025-08-23T01:00:00Z",
   "displayDataId": "s37_blitztest",
   "eventGroup": "Season37_BlitzCups",
   "announcementTime": "2025-08-07T15:00:00Z",
   "regions": [
      "NAW"
   ],
   "regionMappings": {
      "NAW": "NAWCOMP"
   },
   "platforms": [
      "Android",
      "IOS"
   ],
   "platformMappings": {},
   "metadata": {
      "DisqualifyType": "Window",
      "minimumAccountLevel": 15,
      "webId": "S37_BlitzCups"
   },
   "eventWindows": [
      {
         "eventWindowId": "S37_BlitzCups_Event1_NAW",
         "eventTemplateId": "S37_BlitzCups_EventTemplate",
         "countdownBeginTime": "2025-08-22T23:00:00Z",
         "beginTime": "2025-08-23T00:00:00Z",
         "endTime": "2025-08-23T01:00:00Z",
         "round": 0,
         "payoutDelay": 32,
         "isTBD": false,
         "visibility": "public",
         "additionalRequirements": [
            "eula:s37_blitzmobile_rules",
            "adps:g-a81a33a3b9a7",
            "mfa"
         ],
         "teammateEligibility": "all",
         "blackoutPeriods": [],
         "scoreLocations": [
            {
               "leaderboardDefId": "S37_BlitzCups_LeaderboardDef",
               "isMainWindowLeaderboard": true
            }
         ],
         "canLiveSpectate": false,
         "requireAllTokens": [],
         "requireAnyTokens": [],
         "requireNoneTokensCaller": [
            "Permanent_Tournament_Ban"
         ],
         "requireAllTokensCaller": [],
         "requireAnyTokensCaller": [],
         "regionMappings": {},
         "metadata": {
            "RoundType": "Qualifiers",
            "ServerReplays": true
         }
      }
   ],
   "link": {
      "type": "br:tournament",
      "code": "tournament_epicgames_s37_blitzcups_naw"
   }
}