{
   "gameId": "Fortnite",
   "eventId": "epicgames_S37_BlitzMobileCupWeekly_ASIA",
   "beginTime": "2025-08-28T08:00:00Z",
   "endTime": "2025-10-23T09:00:00Z",
   "displayDataId": "s37_blitzweekly",
   "eventGroup": "Season37_BlitzMobileCupWeekly",
   "announcementTime": "2025-08-06T23:00:00Z",
   "regions": [
      "ASIA"
   ],
   "regionMappings": {
      "ASIA": "ASIACOMP"
   },
   "platforms": [
      "Android",
      "IOS"
   ],
   "platformMappings": {},
   "metadata": {
      "AccountLockType": "Window",
      "DisqualifyType": "Window",
      "minimumAccountLevel": 15,
      "webId": "S37_BlitzMobileCupWeekly"
   },
   "eventWindows": [
      {
         "eventWindowId": "S37_BlitzMobileCupWeekly_Event1_ASIA",
         "eventTemplateId": "S37_BlitzCups_EventTemplate",
         "countdownBeginTime": "2025-08-28T07:00:00Z",
         "beginTime": "2025-08-28T08:00:00Z",
         "endTime": "2025-08-28T09:00:00Z",
         "round": 0,
         "payoutDelay": 32,
         "isTBD": false,
         "visibility": "public",
         "additionalRequirements": [
            "eula:s37_blitzmobile_rules",
            "adps:g-a81a33a3b9a7",
            "mfa"
         ],
         "teammateEligibility": "all",
         "blackoutPeriods": [],
         "scoreLocations": [
            {
               "leaderboardDefId": "S37_BlitzMobileCups_LeaderboardDef",
               "isMainWindowLeaderboard": true
            }
         ],
         "canLiveSpectate": false,
         "requireAllTokens": [],
         "requireAnyTokens": [],
         "requireNoneTokensCaller": [
            "EpicAccountPrizingRestriction_v2",
            "Permanent_Tournament_Ban"
         ],
         "requireAllTokensCaller": [],
         "requireAnyTokensCaller": [],
         "regionMappings": {},
         "metadata": {
            "RoundType": "Qualifiers",
            "ServerReplays": true
         }
      },
      {
         "eventWindowId": "S37_BlitzMobileCupWeekly_Event2_ASIA",
         "eventTemplateId": "S37_BlitzCups_EventTemplate",
         "countdownBeginTime": "2025-09-04T07:00:00Z",
         "beginTime": "2025-09-04T08:00:00Z",
         "endTime": "2025-09-04T09:00:00Z",
         "round": 0,
         "payoutDelay": 32,
         "isTBD": false,
         "visibility": "public",
         "additionalRequirements": [
            "eula:s37_blitzmobile_rules",
            "adps:g-a81a33a3b9a7",
            "mfa"
         ],
         "teammateEligibility": "all",
         "blackoutPeriods": [],
         "scoreLocations": [
            {
               "leaderboardDefId": "S37_BlitzMobileCups_LeaderboardDef",
               "isMainWindowLeaderboard": true
            }
         ],
         "canLiveSpectate": false,
         "requireAllTokens": [],
         "requireAnyTokens": [],
         "requireNoneTokensCaller": [
            "EpicAccountPrizingRestriction_v2",
            "Permanent_Tournament_Ban"
         ],
         "requireAllTokensCaller": [],
         "requireAnyTokensCaller": [],
         "regionMappings": {},
         "metadata": {
            "RoundType": "Qualifiers",
            "ServerReplays": true
         }
      },
      {
         "eventWindowId": "S37_BlitzMobileCupWeekly_Event3_ASIA",
         "eventTemplateId": "S37_BlitzCups_EventTemplate",
         "countdownBeginTime": "2025-09-11T07:00:00Z",
         "beginTime": "2025-09-11T08:00:00Z",
         "endTime": "2025-09-11T09:00:00Z",
         "round": 0,
         "payoutDelay": 32,
         "isTBD": false,
         "visibility": "public",
         "additionalRequirements": [
            "eula:s37_blitzmobile_rules",
            "adps:g-a81a33a3b9a7",
            "mfa"
         ],
         "teammateEligibility": "all",
         "blackoutPeriods": [],
         "scoreLocations": [
            {
               "leaderboardDefId": "S37_BlitzMobileCups_LeaderboardDef",
               "isMainWindowLeaderboard": true
            }
         ],
         "canLiveSpectate": false,
         "requireAllTokens": [],
         "requireAnyTokens": [],
         "requireNoneTokensCaller": [
            "EpicAccountPrizingRestriction_v2",
            "Permanent_Tournament_Ban"
         ],
         "requireAllTokensCaller": [],
         "requireAnyTokensCaller": [],
         "regionMappings": {},
         "metadata": {
            "RoundType": "Qualifiers",
            "ServerReplays": true
         }
      },
      {
         "eventWindowId": "S37_BlitzMobileCupWeekly_Event4_ASIA",
         "eventTemplateId": "S37_BlitzCups_EventTemplate",
         "countdownBeginTime": "2025-09-18T07:00:00Z",
         "beginTime": "2025-09-18T08:00:00Z",
         "endTime": "2025-09-18T09:00:00Z",
         "round": 0,
         "payoutDelay": 32,
         "isTBD": false,
         "visibility": "public",
         "additionalRequirements": [
            "eula:s37_blitzmobile_rules",
            "adps:g-a81a33a3b9a7",
            "mfa"
         ],
         "teammateEligibility": "all",
         "blackoutPeriods": [],
         "scoreLocations": [
            {
               "leaderboardDefId": "S37_BlitzMobileCups_LeaderboardDef",
               "isMainWindowLeaderboard": true
            }
         ],
         "canLiveSpectate": false,
         "requireAllTokens": [],
         "requireAnyTokens": [],
         "requireNoneTokensCaller": [
            "EpicAccountPrizingRestriction_v2",
            "Permanent_Tournament_Ban"
         ],
         "requireAllTokensCaller": [],
         "requireAnyTokensCaller": [],
         "regionMappings": {},
         "metadata": {
            "RoundType": "Qualifiers",
            "ServerReplays": true
         }
      },
      {
         "eventWindowId": "S37_BlitzMobileCupWeekly_Event5_ASIA",
         "eventTemplateId": "S37_BlitzCups_EventTemplate",
         "countdownBeginTime": "2025-09-25T07:00:00Z",
         "beginTime": "2025-09-25T08:00:00Z",
         "endTime": "2025-09-25T09:00:00Z",
         "round": 0,
         "payoutDelay": 32,
         "isTBD": false,
         "visibility": "public",
         "additionalRequirements": [
            "eula:s37_blitzmobile_rules",
            "adps:g-a81a33a3b9a7",
            "mfa"
         ],
         "teammateEligibility": "all",
         "blackoutPeriods": [],
         "scoreLocations": [
            {
               "leaderboardDefId": "S37_BlitzMobileCups_LeaderboardDef",
               "isMainWindowLeaderboard": true
            }
         ],
         "canLiveSpectate": false,
         "requireAllTokens": [],
         "requireAnyTokens": [],
         "requireNoneTokensCaller": [
            "EpicAccountPrizingRestriction_v2",
            "Permanent_Tournament_Ban"
         ],
         "requireAllTokensCaller": [],
         "requireAnyTokensCaller": [],
         "regionMappings": {},
         "metadata": {
            "RoundType": "Qualifiers",
            "ServerReplays": true
         }
      },
      {
         "eventWindowId": "S37_BlitzMobileCupWeekly_Event6_ASIA",
         "eventTemplateId": "S37_BlitzCups_EventTemplate",
         "countdownBeginTime": "2025-10-02T07:00:00Z",
         "beginTime": "2025-10-02T08:00:00Z",
         "endTime": "2025-10-02T09:00:00Z",
         "round": 0,
         "payoutDelay": 32,
         "isTBD": false,
         "visibility": "public",
         "additionalRequirements": [
            "eula:s37_blitzmobile_rules",
            "adps:g-a81a33a3b9a7",
            "mfa"
         ],
         "teammateEligibility": "all",
         "blackoutPeriods": [],
         "scoreLocations": [
            {
               "leaderboardDefId": "S37_BlitzMobileCups_LeaderboardDef",
               "isMainWindowLeaderboard": true
            }
         ],
         "canLiveSpectate": false,
         "requireAllTokens": [],
         "requireAnyTokens": [],
         "requireNoneTokensCaller": [
            "EpicAccountPrizingRestriction_v2",
            "Permanent_Tournament_Ban"
         ],
         "requireAllTokensCaller": [],
         "requireAnyTokensCaller": [],
         "regionMappings": {},
         "metadata": {
            "RoundType": "Qualifiers",
            "ServerReplays": true
         }
      },
      {
         "eventWindowId": "S37_BlitzMobileCupWeekly_Event7_ASIA",
         "eventTemplateId": "S37_BlitzCups_EventTemplate",
         "countdownBeginTime": "2025-10-09T07:00:00Z",
         "beginTime": "2025-10-09T08:00:00Z",
         "endTime": "2025-10-09T09:00:00Z",
         "round": 0,
         "payoutDelay": 32,
         "isTBD": false,
         "visibility": "public",
         "additionalRequirements": [
            "eula:s37_blitzmobile_rules",
            "adps:g-a81a33a3b9a7",
            "mfa"
         ],
         "teammateEligibility": "all",
         "blackoutPeriods": [],
         "scoreLocations": [
            {
               "leaderboardDefId": "S37_BlitzMobileCups_LeaderboardDef",
               "isMainWindowLeaderboard": true
            }
         ],
         "canLiveSpectate": false,
         "requireAllTokens": [],
         "requireAnyTokens": [],
         "requireNoneTokensCaller": [
            "EpicAccountPrizingRestriction_v2",
            "Permanent_Tournament_Ban"
         ],
         "requireAllTokensCaller": [],
         "requireAnyTokensCaller": [],
         "regionMappings": {},
         "metadata": {
            "RoundType": "Qualifiers",
            "ServerReplays": true
         }
      },
      {
         "eventWindowId": "S37_BlitzMobileCupWeekly_Event8_ASIA",
         "eventTemplateId": "S37_BlitzCups_EventTemplate",
         "countdownBeginTime": "2025-10-16T07:00:00Z",
         "beginTime": "2025-10-16T08:00:00Z",
         "endTime": "2025-10-16T09:00:00Z",
         "round": 0,
         "payoutDelay": 32,
         "isTBD": false,
         "visibility": "public",
         "additionalRequirements": [
            "eula:s37_blitzmobile_rules",
            "adps:g-a81a33a3b9a7",
            "mfa"
         ],
         "teammateEligibility": "all",
         "blackoutPeriods": [],
         "scoreLocations": [
            {
               "leaderboardDefId": "S37_BlitzMobileCups_LeaderboardDef",
               "isMainWindowLeaderboard": true
            }
         ],
         "canLiveSpectate": false,
         "requireAllTokens": [],
         "requireAnyTokens": [],
         "requireNoneTokensCaller": [
            "EpicAccountPrizingRestriction_v2",
            "Permanent_Tournament_Ban"
         ],
         "requireAllTokensCaller": [],
         "requireAnyTokensCaller": [],
         "regionMappings": {},
         "metadata": {
            "RoundType": "Qualifiers",
            "ServerReplays": true
         }
      },
      {
         "eventWindowId": "S37_BlitzMobileCupWeekly_Event9_ASIA",
         "eventTemplateId": "S37_BlitzCups_EventTemplate",
         "countdownBeginTime": "2025-10-23T07:00:00Z",
         "beginTime": "2025-10-23T08:00:00Z",
         "endTime": "2025-10-23T09:00:00Z",
         "round": 0,
         "payoutDelay": 32,
         "isTBD": false,
         "visibility": "public",
         "additionalRequirements": [
            "eula:s37_blitzmobile_rules",
            "adps:g-a81a33a3b9a7",
            "mfa"
         ],
         "teammateEligibility": "all",
         "blackoutPeriods": [],
         "scoreLocations": [
            {
               "leaderboardDefId": "S37_BlitzMobileCups_LeaderboardDef",
               "isMainWindowLeaderboard": true
            }
         ],
         "canLiveSpectate": false,
         "requireAllTokens": [],
         "requireAnyTokens": [],
         "requireNoneTokensCaller": [
            "EpicAccountPrizingRestriction_v2",
            "Permanent_Tournament_Ban"
         ],
         "requireAllTokensCaller": [],
         "requireAnyTokensCaller": [],
         "regionMappings": {},
         "metadata": {
            "RoundType": "Qualifiers",
            "ServerReplays": true
         }
      }
   ],
   "link": {
      "type": "br:tournament",
      "code": "tournament_epicgames_s37_blitzmobilecupweekly_asia"
   }
}