{
   "gameId": "Fortnite",
   "eventId": "epicgames_S37_ReloadQuickCup_BR",
   "beginTime": "2025-09-05T21:00:00Z",
   "endTime": "2025-10-25T00:30:00Z",
   "displayDataId": "s37_reloadquick",
   "eventGroup": "Season37_ReloadQuick",
   "announcementTime": "2025-08-02T03:00:00Z",
   "regions": [
      "BR"
   ],
   "regionMappings": {
      "BR": "BRCOMP"
   },
   "platforms": [
      "Android",
      "GFN",
      "GFNMobile",
      "Helios",
      "HeliosMobile",
      "IOS",
      "Luna",
      "LunaMobile",
      "Mac",
      "PS4",
      "PS5",
      "Switch",
      "Switch2",
      "Windows",
      "XB1",
      "XCloud",
      "XCloudMobile",
      "XSX",
      "XboxOne",
      "XboxOneGDK"
   ],
   "platformMappings": {},
   "metadata": {
      "AccountLockType": "Window",
      "DisqualifyType": "Window",
      "minimumAccountLevel": 350,
      "requireSystemFeatures": [
         "SecureBoot",
         "CryptoProcessor"
      ],
      "TeamLockType": "Window",
      "tournamentType": "VictoryCup",
      "webId": "S37_ReloadQuickCup"
   },
   "eventWindows": [
      {
         "eventWindowId": "S37_ReloadQuickCup_Event1Group1Round2_BR",
         "eventTemplateId": "EventTemplate_ReloadQuickCups",
         "countdownBeginTime": "2025-09-05T20:10:00Z",
         "beginTime": "2025-09-05T22:15:00Z",
         "endTime": "2025-09-05T23:00:00Z",
         "round": 1,
         "payoutDelay": 24,
         "isTBD": false,
         "visibility": "public",
         "additionalRequirements": [
            "adps:g-a81a33a3b9a7",
            "mfa",
            "eula:s37_reloadrush_rules"
         ],
         "teammateEligibility": "all",
         "blackoutPeriods": [],
         "scoreLocations": [
            {
               "leaderboardDefId": "S37_ReloadQuick_Round2Group1_DefaultLeaderboardDef",
               "isMainWindowLeaderboard": true
            }
         ],
         "canLiveSpectate": false,
         "requireAllTokens": [
            "S37_ReloadQuickCup_Event1Group1Round2_BR"
         ],
         "requireAnyTokens": [],
         "requireNoneTokensCaller": [
            "EpicAccountPrizingRestriction_v2",
            "Permanent_Tournament_Ban"
         ],
         "requireAllTokensCaller": [],
         "requireAnyTokensCaller": [],
         "regionMappings": {},
         "metadata": {
            "RoundType": "Qualifiers",
            "ServerReplays": true
         }
      },
      {
         "eventWindowId": "S37_ReloadQuickCup_Event1Round1_BR",
         "eventTemplateId": "EventTemplate_ReloadQuickCupsRound1",
         "countdownBeginTime": "2025-09-05T19:00:00Z",
         "beginTime": "2025-09-05T21:00:00Z",
         "endTime": "2025-09-05T21:45:00Z",
         "round": 1,
         "payoutDelay": 24,
         "isTBD": false,
         "visibility": "public",
         "additionalRequirements": [
            "adps:g-a81a33a3b9a7",
            "mfa",
            "eula:s37_reloadrush_rules"
         ],
         "teammateEligibility": "all",
         "blackoutPeriods": [],
         "scoreLocations": [
            {
               "leaderboardDefId": "S37_ReloadQuick_Round1_DefaultLeaderboardDef",
               "isMainWindowLeaderboard": true
            }
         ],
         "canLiveSpectate": false,
         "requireAllTokens": [],
         "requireAnyTokens": [
            "S37_CashCup_Qualified"
         ],
         "requireNoneTokensCaller": [
            "EpicAccountPrizingRestriction_v2",
            "Permanent_Tournament_Ban"
         ],
         "requireAllTokensCaller": [],
         "requireAnyTokensCaller": [],
         "regionMappings": {},
         "metadata": {
            "RoundType": "Qualifiers",
            "ServerReplays": true
         }
      },
      {
         "eventWindowId": "S37_ReloadQuickCup_Event1Round3_BR",
         "eventTemplateId": "EventTemplate_ReloadQuickCups",
         "countdownBeginTime": "2025-09-05T21:30:00Z",
         "beginTime": "2025-09-05T23:30:00Z",
         "endTime": "2025-09-06T00:30:00Z",
         "round": 1,
         "payoutDelay": 24,
         "isTBD": false,
         "visibility": "public",
         "additionalRequirements": [
            "adps:g-a81a33a3b9a7",
            "mfa",
            "eula:s37_reloadrush_rules"
         ],
         "teammateEligibility": "all",
         "blackoutPeriods": [],
         "scoreLocations": [
            {
               "leaderboardDefId": "S37_ReloadQuick_Round3_DefaultLeaderboardDef",
               "isMainWindowLeaderboard": true
            }
         ],
         "canLiveSpectate": false,
         "requireAllTokens": [
            "S37_ReloadQuickCup_Event1Round3_BR"
         ],
         "requireAnyTokens": [],
         "requireNoneTokensCaller": [
            "EpicAccountPrizingRestriction_v2",
            "Permanent_Tournament_Ban"
         ],
         "requireAllTokensCaller": [],
         "requireAnyTokensCaller": [],
         "regionMappings": {},
         "metadata": {
            "RoundType": "Qualifiers",
            "ScheduledMatchmakingInitialDelaySeconds": 600,
            "ScheduledMatchmakingMatchDelaySeconds": 1440,
            "ServerReplays": true
         }
      },
      {
         "eventWindowId": "S37_ReloadQuickCup_Event2Group1Round2_BR",
         "eventTemplateId": "EventTemplate_ReloadQuickCups",
         "countdownBeginTime": "2025-09-12T20:10:00Z",
         "beginTime": "2025-09-12T22:15:00Z",
         "endTime": "2025-09-12T23:00:00Z",
         "round": 1,
         "payoutDelay": 24,
         "isTBD": false,
         "visibility": "public",
         "additionalRequirements": [
            "adps:g-a81a33a3b9a7",
            "mfa",
            "eula:s37_reloadrush_rules"
         ],
         "teammateEligibility": "all",
         "blackoutPeriods": [],
         "scoreLocations": [
            {
               "leaderboardDefId": "S37_ReloadQuick_Round2Group1_DefaultLeaderboardDef",
               "isMainWindowLeaderboard": true
            }
         ],
         "canLiveSpectate": false,
         "requireAllTokens": [
            "S37_ReloadQuickCup_Event2Group1Round2_BR"
         ],
         "requireAnyTokens": [],
         "requireNoneTokensCaller": [
            "EpicAccountPrizingRestriction_v2",
            "Permanent_Tournament_Ban"
         ],
         "requireAllTokensCaller": [],
         "requireAnyTokensCaller": [],
         "regionMappings": {},
         "metadata": {
            "RoundType": "Qualifiers",
            "ServerReplays": true
         }
      },
      {
         "eventWindowId": "S37_ReloadQuickCup_Event2Round1_BR",
         "eventTemplateId": "EventTemplate_ReloadQuickCupsRound1",
         "countdownBeginTime": "2025-09-12T19:00:00Z",
         "beginTime": "2025-09-12T21:00:00Z",
         "endTime": "2025-09-12T21:45:00Z",
         "round": 1,
         "payoutDelay": 24,
         "isTBD": false,
         "visibility": "public",
         "additionalRequirements": [
            "adps:g-a81a33a3b9a7",
            "mfa",
            "eula:s37_reloadrush_rules"
         ],
         "teammateEligibility": "all",
         "blackoutPeriods": [],
         "scoreLocations": [
            {
               "leaderboardDefId": "S37_ReloadQuick_Round1_DefaultLeaderboardDef",
               "isMainWindowLeaderboard": true
            }
         ],
         "canLiveSpectate": false,
         "requireAllTokens": [],
         "requireAnyTokens": [
            "S37_CashCup_Qualified"
         ],
         "requireNoneTokensCaller": [
            "EpicAccountPrizingRestriction_v2",
            "Permanent_Tournament_Ban"
         ],
         "requireAllTokensCaller": [],
         "requireAnyTokensCaller": [],
         "regionMappings": {},
         "metadata": {
            "RoundType": "Qualifiers",
            "ServerReplays": true
         }
      },
      {
         "eventWindowId": "S37_ReloadQuickCup_Event2Round3_BR",
         "eventTemplateId": "EventTemplate_ReloadQuickCups",
         "countdownBeginTime": "2025-09-12T21:30:00Z",
         "beginTime": "2025-09-12T23:30:00Z",
         "endTime": "2025-09-13T00:30:00Z",
         "round": 1,
         "payoutDelay": 24,
         "isTBD": false,
         "visibility": "public",
         "additionalRequirements": [
            "adps:g-a81a33a3b9a7",
            "mfa",
            "eula:s37_reloadrush_rules"
         ],
         "teammateEligibility": "all",
         "blackoutPeriods": [],
         "scoreLocations": [
            {
               "leaderboardDefId": "S37_ReloadQuick_Round3_DefaultLeaderboardDef",
               "isMainWindowLeaderboard": true
            }
         ],
         "canLiveSpectate": false,
         "requireAllTokens": [
            "S37_ReloadQuickCup_Event2Round3_BR"
         ],
         "requireAnyTokens": [],
         "requireNoneTokensCaller": [
            "EpicAccountPrizingRestriction_v2",
            "Permanent_Tournament_Ban"
         ],
         "requireAllTokensCaller": [],
         "requireAnyTokensCaller": [],
         "regionMappings": {},
         "metadata": {
            "RoundType": "Qualifiers",
            "ScheduledMatchmakingInitialDelaySeconds": 600,
            "ScheduledMatchmakingMatchDelaySeconds": 1440,
            "ServerReplays": true
         }
      },
      {
         "eventWindowId": "S37_ReloadQuickCup_Event3Group1Round2_BR",
         "eventTemplateId": "EventTemplate_ReloadQuickCups",
         "countdownBeginTime": "2025-09-19T20:10:00Z",
         "beginTime": "2025-09-19T22:15:00Z",
         "endTime": "2025-09-19T23:00:00Z",
         "round": 1,
         "payoutDelay": 24,
         "isTBD": false,
         "visibility": "public",
         "additionalRequirements": [
            "adps:g-a81a33a3b9a7",
            "mfa",
            "eula:s37_reloadrush_rules"
         ],
         "teammateEligibility": "all",
         "blackoutPeriods": [],
         "scoreLocations": [
            {
               "leaderboardDefId": "S37_ReloadQuick_Round2Group1_DefaultLeaderboardDef",
               "isMainWindowLeaderboard": true
            }
         ],
         "canLiveSpectate": false,
         "requireAllTokens": [
            "S37_ReloadQuickCup_Event3Group1Round2_BR"
         ],
         "requireAnyTokens": [],
         "requireNoneTokensCaller": [
            "EpicAccountPrizingRestriction_v2",
            "Permanent_Tournament_Ban"
         ],
         "requireAllTokensCaller": [],
         "requireAnyTokensCaller": [],
         "regionMappings": {},
         "metadata": {
            "RoundType": "Qualifiers",
            "ServerReplays": true
         }
      },
      {
         "eventWindowId": "S37_ReloadQuickCup_Event3Round1_BR",
         "eventTemplateId": "EventTemplate_ReloadQuickCupsRound1",
         "countdownBeginTime": "2025-09-19T19:00:00Z",
         "beginTime": "2025-09-19T21:00:00Z",
         "endTime": "2025-09-19T21:45:00Z",
         "round": 1,
         "payoutDelay": 24,
         "isTBD": false,
         "visibility": "public",
         "additionalRequirements": [
            "adps:g-a81a33a3b9a7",
            "mfa",
            "eula:s37_reloadrush_rules"
         ],
         "teammateEligibility": "all",
         "blackoutPeriods": [],
         "scoreLocations": [
            {
               "leaderboardDefId": "S37_ReloadQuick_Round1_DefaultLeaderboardDef",
               "isMainWindowLeaderboard": true
            }
         ],
         "canLiveSpectate": false,
         "requireAllTokens": [],
         "requireAnyTokens": [
            "S37_CashCup_Qualified"
         ],
         "requireNoneTokensCaller": [
            "EpicAccountPrizingRestriction_v2",
            "Permanent_Tournament_Ban"
         ],
         "requireAllTokensCaller": [],
         "requireAnyTokensCaller": [],
         "regionMappings": {},
         "metadata": {
            "RoundType": "Qualifiers",
            "ServerReplays": true
         }
      },
      {
         "eventWindowId": "S37_ReloadQuickCup_Event3Round3_BR",
         "eventTemplateId": "EventTemplate_ReloadQuickCups",
         "countdownBeginTime": "2025-09-19T21:30:00Z",
         "beginTime": "2025-09-19T23:30:00Z",
         "endTime": "2025-09-20T00:30:00Z",
         "round": 1,
         "payoutDelay": 24,
         "isTBD": false,
         "visibility": "public",
         "additionalRequirements": [
            "adps:g-a81a33a3b9a7",
            "mfa",
            "eula:s37_reloadrush_rules"
         ],
         "teammateEligibility": "all",
         "blackoutPeriods": [],
         "scoreLocations": [
            {
               "leaderboardDefId": "S37_ReloadQuick_Round3_DefaultLeaderboardDef",
               "isMainWindowLeaderboard": true
            }
         ],
         "canLiveSpectate": false,
         "requireAllTokens": [
            "S37_ReloadQuickCup_Event3Round3_BR"
         ],
         "requireAnyTokens": [],
         "requireNoneTokensCaller": [
            "EpicAccountPrizingRestriction_v2",
            "Permanent_Tournament_Ban"
         ],
         "requireAllTokensCaller": [],
         "requireAnyTokensCaller": [],
         "regionMappings": {},
         "metadata": {
            "RoundType": "Qualifiers",
            "ScheduledMatchmakingInitialDelaySeconds": 600,
            "ScheduledMatchmakingMatchDelaySeconds": 1440,
            "ServerReplays": true
         }
      },
      {
         "eventWindowId": "S37_ReloadQuickCup_Event4Group1Round2_BR",
         "eventTemplateId": "EventTemplate_ReloadQuickCups",
         "countdownBeginTime": "2025-09-26T20:10:00Z",
         "beginTime": "2025-09-26T22:15:00Z",
         "endTime": "2025-09-26T23:00:00Z",
         "round": 1,
         "payoutDelay": 24,
         "isTBD": false,
         "visibility": "public",
         "additionalRequirements": [
            "adps:g-a81a33a3b9a7",
            "mfa",
            "eula:s37_reloadrush_rules"
         ],
         "teammateEligibility": "all",
         "blackoutPeriods": [],
         "scoreLocations": [
            {
               "leaderboardDefId": "S37_ReloadQuick_Round2Group1_DefaultLeaderboardDef",
               "isMainWindowLeaderboard": true
            }
         ],
         "canLiveSpectate": false,
         "requireAllTokens": [
            "S37_ReloadQuickCup_Event4Group1Round2_BR"
         ],
         "requireAnyTokens": [],
         "requireNoneTokensCaller": [
            "EpicAccountPrizingRestriction_v2",
            "Permanent_Tournament_Ban"
         ],
         "requireAllTokensCaller": [],
         "requireAnyTokensCaller": [],
         "regionMappings": {},
         "metadata": {
            "RoundType": "Qualifiers",
            "ServerReplays": true
         }
      },
      {
         "eventWindowId": "S37_ReloadQuickCup_Event4Round1_BR",
         "eventTemplateId": "EventTemplate_ReloadQuickCupsRound1",
         "countdownBeginTime": "2025-09-26T19:00:00Z",
         "beginTime": "2025-09-26T21:00:00Z",
         "endTime": "2025-09-26T21:45:00Z",
         "round": 1,
         "payoutDelay": 24,
         "isTBD": false,
         "visibility": "public",
         "additionalRequirements": [
            "adps:g-a81a33a3b9a7",
            "mfa",
            "eula:s37_reloadrush_rules"
         ],
         "teammateEligibility": "all",
         "blackoutPeriods": [],
         "scoreLocations": [
            {
               "leaderboardDefId": "S37_ReloadQuick_Round1_DefaultLeaderboardDef",
               "isMainWindowLeaderboard": true
            }
         ],
         "canLiveSpectate": false,
         "requireAllTokens": [],
         "requireAnyTokens": [
            "S37_CashCup_Qualified"
         ],
         "requireNoneTokensCaller": [
            "EpicAccountPrizingRestriction_v2",
            "Permanent_Tournament_Ban"
         ],
         "requireAllTokensCaller": [],
         "requireAnyTokensCaller": [],
         "regionMappings": {},
         "metadata": {
            "RoundType": "Qualifiers",
            "ServerReplays": true
         }
      },
      {
         "eventWindowId": "S37_ReloadQuickCup_Event4Round3_BR",
         "eventTemplateId": "EventTemplate_ReloadQuickCups",
         "countdownBeginTime": "2025-09-26T21:30:00Z",
         "beginTime": "2025-09-26T23:30:00Z",
         "endTime": "2025-09-27T00:30:00Z",
         "round": 1,
         "payoutDelay": 24,
         "isTBD": false,
         "visibility": "public",
         "additionalRequirements": [
            "adps:g-a81a33a3b9a7",
            "mfa",
            "eula:s37_reloadrush_rules"
         ],
         "teammateEligibility": "all",
         "blackoutPeriods": [],
         "scoreLocations": [
            {
               "leaderboardDefId": "S37_ReloadQuick_Round3_DefaultLeaderboardDef",
               "isMainWindowLeaderboard": true
            }
         ],
         "canLiveSpectate": false,
         "requireAllTokens": [
            "S37_ReloadQuickCup_Event4Round3_BR"
         ],
         "requireAnyTokens": [],
         "requireNoneTokensCaller": [
            "EpicAccountPrizingRestriction_v2",
            "Permanent_Tournament_Ban"
         ],
         "requireAllTokensCaller": [],
         "requireAnyTokensCaller": [],
         "regionMappings": {},
         "metadata": {
            "RoundType": "Qualifiers",
            "ScheduledMatchmakingInitialDelaySeconds": 600,
            "ScheduledMatchmakingMatchDelaySeconds": 1440,
            "ServerReplays": true
         }
      },
      {
         "eventWindowId": "S37_ReloadQuickCup_Event5Group1Round2_BR",
         "eventTemplateId": "EventTemplate_ReloadQuickCups",
         "countdownBeginTime": "2025-10-03T20:10:00Z",
         "beginTime": "2025-10-03T22:15:00Z",
         "endTime": "2025-10-03T23:00:00Z",
         "round": 1,
         "payoutDelay": 24,
         "isTBD": false,
         "visibility": "public",
         "additionalRequirements": [
            "adps:g-a81a33a3b9a7",
            "mfa",
            "eula:s37_reloadrush_rules"
         ],
         "teammateEligibility": "all",
         "blackoutPeriods": [],
         "scoreLocations": [
            {
               "leaderboardDefId": "S37_ReloadQuick_Round2Group1_DefaultLeaderboardDef",
               "isMainWindowLeaderboard": true
            }
         ],
         "canLiveSpectate": false,
         "requireAllTokens": [
            "S37_ReloadQuickCup_Event5Group1Round2_BR"
         ],
         "requireAnyTokens": [],
         "requireNoneTokensCaller": [
            "EpicAccountPrizingRestriction_v2",
            "Permanent_Tournament_Ban"
         ],
         "requireAllTokensCaller": [],
         "requireAnyTokensCaller": [],
         "regionMappings": {},
         "metadata": {
            "RoundType": "Qualifiers",
            "ServerReplays": true
         }
      },
      {
         "eventWindowId": "S37_ReloadQuickCup_Event5Round1_BR",
         "eventTemplateId": "EventTemplate_ReloadQuickCupsRound1",
         "countdownBeginTime": "2025-10-03T19:00:00Z",
         "beginTime": "2025-10-03T21:00:00Z",
         "endTime": "2025-10-03T21:45:00Z",
         "round": 1,
         "payoutDelay": 24,
         "isTBD": false,
         "visibility": "public",
         "additionalRequirements": [
            "adps:g-a81a33a3b9a7",
            "mfa",
            "eula:s37_reloadrush_rules"
         ],
         "teammateEligibility": "all",
         "blackoutPeriods": [],
         "scoreLocations": [
            {
               "leaderboardDefId": "S37_ReloadQuick_Round1_DefaultLeaderboardDef",
               "isMainWindowLeaderboard": true
            }
         ],
         "canLiveSpectate": false,
         "requireAllTokens": [],
         "requireAnyTokens": [
            "S37_CashCup_Qualified"
         ],
         "requireNoneTokensCaller": [
            "EpicAccountPrizingRestriction_v2",
            "Permanent_Tournament_Ban"
         ],
         "requireAllTokensCaller": [],
         "requireAnyTokensCaller": [],
         "regionMappings": {},
         "metadata": {
            "RoundType": "Qualifiers",
            "ServerReplays": true
         }
      },
      {
         "eventWindowId": "S37_ReloadQuickCup_Event5Round3_BR",
         "eventTemplateId": "EventTemplate_ReloadQuickCups",
         "countdownBeginTime": "2025-10-03T21:30:00Z",
         "beginTime": "2025-10-03T23:30:00Z",
         "endTime": "2025-10-04T00:30:00Z",
         "round": 1,
         "payoutDelay": 24,
         "isTBD": false,
         "visibility": "public",
         "additionalRequirements": [
            "adps:g-a81a33a3b9a7",
            "mfa",
            "eula:s37_reloadrush_rules"
         ],
         "teammateEligibility": "all",
         "blackoutPeriods": [],
         "scoreLocations": [
            {
               "leaderboardDefId": "S37_ReloadQuick_Round3_DefaultLeaderboardDef",
               "isMainWindowLeaderboard": true
            }
         ],
         "canLiveSpectate": false,
         "requireAllTokens": [
            "S37_ReloadQuickCup_Event5Round3_BR"
         ],
         "requireAnyTokens": [],
         "requireNoneTokensCaller": [
            "EpicAccountPrizingRestriction_v2",
            "Permanent_Tournament_Ban"
         ],
         "requireAllTokensCaller": [],
         "requireAnyTokensCaller": [],
         "regionMappings": {},
         "metadata": {
            "RoundType": "Qualifiers",
            "ScheduledMatchmakingInitialDelaySeconds": 600,
            "ScheduledMatchmakingMatchDelaySeconds": 1440,
            "ServerReplays": true
         }
      },
      {
         "eventWindowId": "S37_ReloadQuickCup_Event6Group1Round2_BR",
         "eventTemplateId": "EventTemplate_ReloadQuickCups",
         "countdownBeginTime": "2025-10-09T20:10:00Z",
         "beginTime": "2025-10-09T22:15:00Z",
         "endTime": "2025-10-09T23:00:00Z",
         "round": 1,
         "payoutDelay": 24,
         "isTBD": false,
         "visibility": "public",
         "additionalRequirements": [
            "adps:g-a81a33a3b9a7",
            "mfa",
            "eula:s37_reloadrush_rules"
         ],
         "teammateEligibility": "all",
         "blackoutPeriods": [],
         "scoreLocations": [
            {
               "leaderboardDefId": "S37_ReloadQuick_Round2Group1_DefaultLeaderboardDef",
               "isMainWindowLeaderboard": true
            }
         ],
         "canLiveSpectate": false,
         "requireAllTokens": [
            "S37_ReloadQuickCup_Event6Group1Round2_BR"
         ],
         "requireAnyTokens": [],
         "requireNoneTokensCaller": [
            "EpicAccountPrizingRestriction_v2",
            "Permanent_Tournament_Ban"
         ],
         "requireAllTokensCaller": [],
         "requireAnyTokensCaller": [],
         "regionMappings": {},
         "metadata": {
            "RoundType": "Qualifiers",
            "ServerReplays": true
         }
      },
      {
         "eventWindowId": "S37_ReloadQuickCup_Event6Round1_BR",
         "eventTemplateId": "EventTemplate_ReloadQuickCupsRound1",
         "countdownBeginTime": "2025-10-09T19:00:00Z",
         "beginTime": "2025-10-09T21:00:00Z",
         "endTime": "2025-10-09T21:45:00Z",
         "round": 1,
         "payoutDelay": 24,
         "isTBD": false,
         "visibility": "public",
         "additionalRequirements": [
            "adps:g-a81a33a3b9a7",
            "mfa",
            "eula:s37_reloadrush_rules"
         ],
         "teammateEligibility": "all",
         "blackoutPeriods": [],
         "scoreLocations": [
            {
               "leaderboardDefId": "S37_ReloadQuick_Round1_DefaultLeaderboardDef",
               "isMainWindowLeaderboard": true
            }
         ],
         "canLiveSpectate": false,
         "requireAllTokens": [],
         "requireAnyTokens": [
            "S37_CashCup_Qualified"
         ],
         "requireNoneTokensCaller": [
            "EpicAccountPrizingRestriction_v2",
            "Permanent_Tournament_Ban"
         ],
         "requireAllTokensCaller": [],
         "requireAnyTokensCaller": [],
         "regionMappings": {},
         "metadata": {
            "RoundType": "Qualifiers",
            "ServerReplays": true
         }
      },
      {
         "eventWindowId": "S37_ReloadQuickCup_Event6Round3_BR",
         "eventTemplateId": "EventTemplate_ReloadQuickCups",
         "countdownBeginTime": "2025-10-09T21:30:00Z",
         "beginTime": "2025-10-09T23:30:00Z",
         "endTime": "2025-10-10T00:30:00Z",
         "round": 1,
         "payoutDelay": 24,
         "isTBD": false,
         "visibility": "public",
         "additionalRequirements": [
            "adps:g-a81a33a3b9a7",
            "mfa",
            "eula:s37_reloadrush_rules"
         ],
         "teammateEligibility": "all",
         "blackoutPeriods": [],
         "scoreLocations": [
            {
               "leaderboardDefId": "S37_ReloadQuick_Round3_DefaultLeaderboardDef",
               "isMainWindowLeaderboard": true
            }
         ],
         "canLiveSpectate": false,
         "requireAllTokens": [
            "S37_ReloadQuickCup_Event6Round3_BR"
         ],
         "requireAnyTokens": [],
         "requireNoneTokensCaller": [
            "EpicAccountPrizingRestriction_v2",
            "Permanent_Tournament_Ban"
         ],
         "requireAllTokensCaller": [],
         "requireAnyTokensCaller": [],
         "regionMappings": {},
         "metadata": {
            "RoundType": "Qualifiers",
            "ScheduledMatchmakingInitialDelaySeconds": 600,
            "ScheduledMatchmakingMatchDelaySeconds": 1440,
            "ServerReplays": true
         }
      },
      {
         "eventWindowId": "S37_ReloadQuickCup_Event7Group1Round2_BR",
         "eventTemplateId": "EventTemplate_ReloadQuickCups",
         "countdownBeginTime": "2025-10-10T20:10:00Z",
         "beginTime": "2025-10-10T22:15:00Z",
         "endTime": "2025-10-10T23:00:00Z",
         "round": 1,
         "payoutDelay": 24,
         "isTBD": false,
         "visibility": "public",
         "additionalRequirements": [
            "adps:g-a81a33a3b9a7",
            "mfa",
            "eula:s37_reloadrush_rules"
         ],
         "teammateEligibility": "all",
         "blackoutPeriods": [],
         "scoreLocations": [
            {
               "leaderboardDefId": "S37_ReloadQuick_Round2Group1_DefaultLeaderboardDef",
               "isMainWindowLeaderboard": true
            }
         ],
         "canLiveSpectate": false,
         "requireAllTokens": [
            "S37_ReloadQuickCup_Event7Group1Round2_BR"
         ],
         "requireAnyTokens": [],
         "requireNoneTokensCaller": [
            "EpicAccountPrizingRestriction_v2",
            "Permanent_Tournament_Ban"
         ],
         "requireAllTokensCaller": [],
         "requireAnyTokensCaller": [],
         "regionMappings": {},
         "metadata": {
            "RoundType": "Qualifiers",
            "ServerReplays": true
         }
      },
      {
         "eventWindowId": "S37_ReloadQuickCup_Event7Round1_BR",
         "eventTemplateId": "EventTemplate_ReloadQuickCupsRound1",
         "countdownBeginTime": "2025-10-10T19:00:00Z",
         "beginTime": "2025-10-10T21:00:00Z",
         "endTime": "2025-10-10T21:45:00Z",
         "round": 1,
         "payoutDelay": 24,
         "isTBD": false,
         "visibility": "public",
         "additionalRequirements": [
            "adps:g-a81a33a3b9a7",
            "mfa",
            "eula:s37_reloadrush_rules"
         ],
         "teammateEligibility": "all",
         "blackoutPeriods": [],
         "scoreLocations": [
            {
               "leaderboardDefId": "S37_ReloadQuick_Round1_DefaultLeaderboardDef",
               "isMainWindowLeaderboard": true
            }
         ],
         "canLiveSpectate": false,
         "requireAllTokens": [],
         "requireAnyTokens": [
            "S37_CashCup_Qualified"
         ],
         "requireNoneTokensCaller": [
            "EpicAccountPrizingRestriction_v2",
            "Permanent_Tournament_Ban"
         ],
         "requireAllTokensCaller": [],
         "requireAnyTokensCaller": [],
         "regionMappings": {},
         "metadata": {
            "RoundType": "Qualifiers",
            "ServerReplays": true
         }
      },
      {
         "eventWindowId": "S37_ReloadQuickCup_Event7Round3_BR",
         "eventTemplateId": "EventTemplate_ReloadQuickCups",
         "countdownBeginTime": "2025-10-10T21:30:00Z",
         "beginTime": "2025-10-10T23:30:00Z",
         "endTime": "2025-10-11T00:30:00Z",
         "round": 1,
         "payoutDelay": 24,
         "isTBD": false,
         "visibility": "public",
         "additionalRequirements": [
            "adps:g-a81a33a3b9a7",
            "mfa",
            "eula:s37_reloadrush_rules"
         ],
         "teammateEligibility": "all",
         "blackoutPeriods": [],
         "scoreLocations": [
            {
               "leaderboardDefId": "S37_ReloadQuick_Round3_DefaultLeaderboardDef",
               "isMainWindowLeaderboard": true
            }
         ],
         "canLiveSpectate": false,
         "requireAllTokens": [
            "S37_ReloadQuickCup_Event7Round3_BR"
         ],
         "requireAnyTokens": [],
         "requireNoneTokensCaller": [
            "EpicAccountPrizingRestriction_v2",
            "Permanent_Tournament_Ban"
         ],
         "requireAllTokensCaller": [],
         "requireAnyTokensCaller": [],
         "regionMappings": {},
         "metadata": {
            "RoundType": "Qualifiers",
            "ScheduledMatchmakingInitialDelaySeconds": 600,
            "ScheduledMatchmakingMatchDelaySeconds": 1440,
            "ServerReplays": true
         }
      },
      {
         "eventWindowId": "S37_ReloadQuickCup_Event8Group1Round2_BR",
         "eventTemplateId": "EventTemplate_ReloadQuickCups",
         "countdownBeginTime": "2025-10-17T20:10:00Z",
         "beginTime": "2025-10-17T22:15:00Z",
         "endTime": "2025-10-17T23:00:00Z",
         "round": 1,
         "payoutDelay": 24,
         "isTBD": false,
         "visibility": "public",
         "additionalRequirements": [
            "adps:g-a81a33a3b9a7",
            "mfa",
            "eula:s37_reloadrush_rules"
         ],
         "teammateEligibility": "all",
         "blackoutPeriods": [],
         "scoreLocations": [
            {
               "leaderboardDefId": "S37_ReloadQuick_Round2Group1_DefaultLeaderboardDef",
               "isMainWindowLeaderboard": true
            }
         ],
         "canLiveSpectate": false,
         "requireAllTokens": [
            "S37_ReloadQuickCup_Event8Group1Round2_BR"
         ],
         "requireAnyTokens": [],
         "requireNoneTokensCaller": [
            "EpicAccountPrizingRestriction_v2",
            "Permanent_Tournament_Ban"
         ],
         "requireAllTokensCaller": [],
         "requireAnyTokensCaller": [],
         "regionMappings": {},
         "metadata": {
            "RoundType": "Qualifiers",
            "ServerReplays": true
         }
      },
      {
         "eventWindowId": "S37_ReloadQuickCup_Event8Round1_BR",
         "eventTemplateId": "EventTemplate_ReloadQuickCupsRound1",
         "countdownBeginTime": "2025-10-17T19:00:00Z",
         "beginTime": "2025-10-17T21:00:00Z",
         "endTime": "2025-10-17T21:45:00Z",
         "round": 1,
         "payoutDelay": 24,
         "isTBD": false,
         "visibility": "public",
         "additionalRequirements": [
            "adps:g-a81a33a3b9a7",
            "mfa",
            "eula:s37_reloadrush_rules"
         ],
         "teammateEligibility": "all",
         "blackoutPeriods": [],
         "scoreLocations": [
            {
               "leaderboardDefId": "S37_ReloadQuick_Round1_DefaultLeaderboardDef",
               "isMainWindowLeaderboard": true
            }
         ],
         "canLiveSpectate": false,
         "requireAllTokens": [],
         "requireAnyTokens": [
            "S37_CashCup_Qualified"
         ],
         "requireNoneTokensCaller": [
            "EpicAccountPrizingRestriction_v2",
            "Permanent_Tournament_Ban"
         ],
         "requireAllTokensCaller": [],
         "requireAnyTokensCaller": [],
         "regionMappings": {},
         "metadata": {
            "RoundType": "Qualifiers",
            "ServerReplays": true
         }
      },
      {
         "eventWindowId": "S37_ReloadQuickCup_Event8Round3_BR",
         "eventTemplateId": "EventTemplate_ReloadQuickCups",
         "countdownBeginTime": "2025-10-17T21:30:00Z",
         "beginTime": "2025-10-17T23:30:00Z",
         "endTime": "2025-10-18T00:30:00Z",
         "round": 1,
         "payoutDelay": 24,
         "isTBD": false,
         "visibility": "public",
         "additionalRequirements": [
            "adps:g-a81a33a3b9a7",
            "mfa",
            "eula:s37_reloadrush_rules"
         ],
         "teammateEligibility": "all",
         "blackoutPeriods": [],
         "scoreLocations": [
            {
               "leaderboardDefId": "S37_ReloadQuick_Round3_DefaultLeaderboardDef",
               "isMainWindowLeaderboard": true
            }
         ],
         "canLiveSpectate": false,
         "requireAllTokens": [
            "S37_ReloadQuickCup_Event8Round3_BR"
         ],
         "requireAnyTokens": [],
         "requireNoneTokensCaller": [
            "EpicAccountPrizingRestriction_v2",
            "Permanent_Tournament_Ban"
         ],
         "requireAllTokensCaller": [],
         "requireAnyTokensCaller": [],
         "regionMappings": {},
         "metadata": {
            "RoundType": "Qualifiers",
            "ScheduledMatchmakingInitialDelaySeconds": 600,
            "ScheduledMatchmakingMatchDelaySeconds": 1440,
            "ServerReplays": true
         }
      },
      {
         "eventWindowId": "S37_ReloadQuickCup_Event9Group1Round2_BR",
         "eventTemplateId": "EventTemplate_ReloadQuickCups",
         "countdownBeginTime": "2025-10-24T20:10:00Z",
         "beginTime": "2025-10-24T22:15:00Z",
         "endTime": "2025-10-24T23:00:00Z",
         "round": 1,
         "payoutDelay": 24,
         "isTBD": false,
         "visibility": "public",
         "additionalRequirements": [
            "adps:g-a81a33a3b9a7",
            "mfa",
            "eula:s37_reloadrush_rules"
         ],
         "teammateEligibility": "all",
         "blackoutPeriods": [],
         "scoreLocations": [
            {
               "leaderboardDefId": "S37_ReloadQuick_Round2Group1_DefaultLeaderboardDef",
               "isMainWindowLeaderboard": true
            }
         ],
         "canLiveSpectate": false,
         "requireAllTokens": [
            "S37_ReloadQuickCup_Event9Group1Round2_BR"
         ],
         "requireAnyTokens": [],
         "requireNoneTokensCaller": [
            "EpicAccountPrizingRestriction_v2",
            "Permanent_Tournament_Ban"
         ],
         "requireAllTokensCaller": [],
         "requireAnyTokensCaller": [],
         "regionMappings": {},
         "metadata": {
            "RoundType": "Qualifiers",
            "ServerReplays": true
         }
      },
      {
         "eventWindowId": "S37_ReloadQuickCup_Event9Round1_BR",
         "eventTemplateId": "EventTemplate_ReloadQuickCupsRound1",
         "countdownBeginTime": "2025-10-24T19:00:00Z",
         "beginTime": "2025-10-24T21:00:00Z",
         "endTime": "2025-10-24T21:45:00Z",
         "round": 1,
         "payoutDelay": 24,
         "isTBD": false,
         "visibility": "public",
         "additionalRequirements": [
            "adps:g-a81a33a3b9a7",
            "mfa",
            "eula:s37_reloadrush_rules"
         ],
         "teammateEligibility": "all",
         "blackoutPeriods": [],
         "scoreLocations": [
            {
               "leaderboardDefId": "S37_ReloadQuick_Round1_DefaultLeaderboardDef",
               "isMainWindowLeaderboard": true
            }
         ],
         "canLiveSpectate": false,
         "requireAllTokens": [],
         "requireAnyTokens": [
            "S37_CashCup_Qualified"
         ],
         "requireNoneTokensCaller": [
            "EpicAccountPrizingRestriction_v2",
            "Permanent_Tournament_Ban"
         ],
         "requireAllTokensCaller": [],
         "requireAnyTokensCaller": [],
         "regionMappings": {},
         "metadata": {
            "RoundType": "Qualifiers",
            "ServerReplays": true
         }
      },
      {
         "eventWindowId": "S37_ReloadQuickCup_Event9Round3_BR",
         "eventTemplateId": "EventTemplate_ReloadQuickCups",
         "countdownBeginTime": "2025-10-24T21:30:00Z",
         "beginTime": "2025-10-24T23:30:00Z",
         "endTime": "2025-10-25T00:30:00Z",
         "round": 1,
         "payoutDelay": 24,
         "isTBD": false,
         "visibility": "public",
         "additionalRequirements": [
            "adps:g-a81a33a3b9a7",
            "mfa",
            "eula:s37_reloadrush_rules"
         ],
         "teammateEligibility": "all",
         "blackoutPeriods": [],
         "scoreLocations": [
            {
               "leaderboardDefId": "S37_ReloadQuick_Round3_DefaultLeaderboardDef",
               "isMainWindowLeaderboard": true
            }
         ],
         "canLiveSpectate": false,
         "requireAllTokens": [
            "S37_ReloadQuickCup_Event9Round3_BR"
         ],
         "requireAnyTokens": [],
         "requireNoneTokensCaller": [
            "EpicAccountPrizingRestriction_v2",
            "Permanent_Tournament_Ban"
         ],
         "requireAllTokensCaller": [],
         "requireAnyTokensCaller": [],
         "regionMappings": {},
         "metadata": {
            "RoundType": "Qualifiers",
            "ScheduledMatchmakingInitialDelaySeconds": 600,
            "ScheduledMatchmakingMatchDelaySeconds": 1440,
            "ServerReplays": true
         }
      }
   ],
   "link": {
      "type": "br:tournament",
      "code": "tournament_epicgames_s37_reloadquickcup_br"
   }
}