{
   "gameId": "Fortnite",
   "eventId": "epicgames_S37_SoloSeriesCup_NAC",
   "beginTime": "2025-09-11T23:00:00Z",
   "endTime": "2025-10-27T02:00:00Z",
   "displayDataId": "s37_soloseries",
   "eventGroup": "Season37_SoloSeriesCup",
   "announcementTime": "2025-06-07T05:00:00Z",
   "regions": [
      "NAC",
      "NAE"
   ],
   "regionMappings": {
      "NAC": "NACCOMP",
      "NAE": "NACCOMP"
   },
   "platforms": [
      "Android",
      "GFN",
      "GFNMobile",
      "Helios",
      "HeliosMobile",
      "IOS",
      "Luna",
      "LunaMobile",
      "Mac",
      "PS4",
      "PS5",
      "Switch",
      "Switch2",
      "Windows",
      "XB1",
      "XCloud",
      "XCloudMobile",
      "XSX",
      "XboxOne",
      "XboxOneGDK"
   ],
   "platformMappings": {},
   "metadata": {
      "AccountLockType": "Window",
      "DisqualifyType": "Event",
      "minimumAccountLevel": 350,
      "requireSystemFeatures": [
         "SecureBoot",
         "CryptoProcessor"
      ],
      "TeamLockType": "Window",
      "tournamentType": "CashCup",
      "webId": "S37_SoloSeriesCup"
   },
   "eventWindows": [
      {
         "eventWindowId": "S37_SoloSeriesCup_Event1_NAC",
         "eventTemplateId": "EventTemplate_S37_SoloSeriesCup",
         "countdownBeginTime": "2025-09-11T21:00:00Z",
         "beginTime": "2025-09-11T23:00:00Z",
         "endTime": "2025-09-12T02:00:00Z",
         "round": 1,
         "payoutDelay": 32,
         "isTBD": false,
         "visibility": "public",
         "additionalRequirements": [
            "eula:s37_soloseries_rules",
            "adps:g-a81a33a3b9a7",
            "mfa",
            [
               "currentRanking:ranked-br:6",
               "currentRanking:ranked-zb:6",
               "currentRanking:ranked_blastberry_build:6",
               "currentRanking:ranked_blastberry_nobuild:6"
            ]
         ],
         "teammateEligibility": "all",
         "blackoutPeriods": [],
         "scoreLocations": [
            {
               "leaderboardDefId": "S37_SoloSeriesCup_DefaultLeaderboardDef",
               "isMainWindowLeaderboard": true
            },
            {
               "leaderboardDefId": "S37_SoloSeriesCup_SeriesLeaderboardDef",
               "isMainWindowLeaderboard": false
            }
         ],
         "canLiveSpectate": false,
         "requireAllTokens": [
            "S37_CashCup_Qualified"
         ],
         "requireAnyTokens": [],
         "requireNoneTokensCaller": [
            "EpicAccountPrizingRestriction_v2",
            "Permanent_Tournament_Ban"
         ],
         "requireAllTokensCaller": [],
         "requireAnyTokensCaller": [],
         "regionMappings": {},
         "metadata": {
            "asyncPayoutsExclusiveLeaderboardDefs": [
               "S37_SoloSeriesCup_SeriesLeaderboardDef"
            ],
            "RoundType": "Qualifiers",
            "ServerReplays": true
         }
      },
      {
         "eventWindowId": "S37_SoloSeriesCup_Event2_NAC",
         "eventTemplateId": "EventTemplate_S37_SoloSeriesCup",
         "countdownBeginTime": "2025-09-21T21:00:00Z",
         "beginTime": "2025-09-21T23:00:00Z",
         "endTime": "2025-09-22T02:00:00Z",
         "round": 2,
         "payoutDelay": 32,
         "isTBD": false,
         "visibility": "public",
         "additionalRequirements": [
            "eula:s37_soloseries_rules",
            "adps:g-a81a33a3b9a7",
            "mfa",
            [
               "currentRanking:ranked-br:6",
               "currentRanking:ranked-zb:6",
               "currentRanking:ranked_blastberry_build:6",
               "currentRanking:ranked_blastberry_nobuild:6"
            ]
         ],
         "teammateEligibility": "all",
         "blackoutPeriods": [],
         "scoreLocations": [
            {
               "leaderboardDefId": "S37_SoloSeriesCup_DefaultLeaderboardDef",
               "isMainWindowLeaderboard": true
            },
            {
               "leaderboardDefId": "S37_SoloSeriesCup_SeriesLeaderboardDef",
               "isMainWindowLeaderboard": false
            }
         ],
         "canLiveSpectate": false,
         "requireAllTokens": [
            "S37_CashCup_Qualified"
         ],
         "requireAnyTokens": [],
         "requireNoneTokensCaller": [
            "EpicAccountPrizingRestriction_v2",
            "Permanent_Tournament_Ban"
         ],
         "requireAllTokensCaller": [],
         "requireAnyTokensCaller": [],
         "regionMappings": {},
         "metadata": {
            "asyncPayoutsExclusiveLeaderboardDefs": [
               "S37_SoloSeriesCup_SeriesLeaderboardDef"
            ],
            "RoundType": "Qualifiers",
            "ServerReplays": true
         }
      },
      {
         "eventWindowId": "S37_SoloSeriesCup_Event3_NAC",
         "eventTemplateId": "EventTemplate_S37_SoloSeriesCup",
         "countdownBeginTime": "2025-09-28T21:00:00Z",
         "beginTime": "2025-09-28T23:00:00Z",
         "endTime": "2025-09-29T02:00:00Z",
         "round": 3,
         "payoutDelay": 32,
         "isTBD": false,
         "visibility": "public",
         "additionalRequirements": [
            "eula:s37_soloseries_rules",
            "adps:g-a81a33a3b9a7",
            "mfa",
            [
               "currentRanking:ranked-br:6",
               "currentRanking:ranked-zb:6",
               "currentRanking:ranked_blastberry_build:6",
               "currentRanking:ranked_blastberry_nobuild:6"
            ]
         ],
         "teammateEligibility": "all",
         "blackoutPeriods": [],
         "scoreLocations": [
            {
               "leaderboardDefId": "S37_SoloSeriesCup_DefaultLeaderboardDef",
               "isMainWindowLeaderboard": true
            },
            {
               "leaderboardDefId": "S37_SoloSeriesCup_SeriesLeaderboardDef",
               "isMainWindowLeaderboard": false
            }
         ],
         "canLiveSpectate": false,
         "requireAllTokens": [
            "S37_CashCup_Qualified"
         ],
         "requireAnyTokens": [],
         "requireNoneTokensCaller": [
            "EpicAccountPrizingRestriction_v2",
            "Permanent_Tournament_Ban"
         ],
         "requireAllTokensCaller": [],
         "requireAnyTokensCaller": [],
         "regionMappings": {},
         "metadata": {
            "asyncPayoutsExclusiveLeaderboardDefs": [
               "S37_SoloSeriesCup_SeriesLeaderboardDef"
            ],
            "RoundType": "Qualifiers",
            "ServerReplays": true
         }
      },
      {
         "eventWindowId": "S37_SoloSeriesCup_Event4_NAC",
         "eventTemplateId": "EventTemplate_S37_SoloSeriesCup",
         "countdownBeginTime": "2025-10-05T21:00:00Z",
         "beginTime": "2025-10-05T23:00:00Z",
         "endTime": "2025-10-06T02:00:00Z",
         "round": 4,
         "payoutDelay": 32,
         "isTBD": false,
         "visibility": "public",
         "additionalRequirements": [
            "eula:s37_soloseries_rules",
            "adps:g-a81a33a3b9a7",
            "mfa",
            [
               "currentRanking:ranked-br:6",
               "currentRanking:ranked-zb:6",
               "currentRanking:ranked_blastberry_build:6",
               "currentRanking:ranked_blastberry_nobuild:6"
            ]
         ],
         "teammateEligibility": "all",
         "blackoutPeriods": [],
         "scoreLocations": [
            {
               "leaderboardDefId": "S37_SoloSeriesCup_DefaultLeaderboardDef",
               "isMainWindowLeaderboard": true
            },
            {
               "leaderboardDefId": "S37_SoloSeriesCup_SeriesLeaderboardDef",
               "isMainWindowLeaderboard": false
            }
         ],
         "canLiveSpectate": false,
         "requireAllTokens": [
            "S37_CashCup_Qualified"
         ],
         "requireAnyTokens": [],
         "requireNoneTokensCaller": [
            "EpicAccountPrizingRestriction_v2",
            "Permanent_Tournament_Ban"
         ],
         "requireAllTokensCaller": [],
         "requireAnyTokensCaller": [],
         "regionMappings": {},
         "metadata": {
            "asyncPayoutsExclusiveLeaderboardDefs": [
               "S37_SoloSeriesCup_SeriesLeaderboardDef"
            ],
            "RoundType": "Qualifiers",
            "ServerReplays": true
         }
      },
      {
         "eventWindowId": "S37_SoloSeriesCup_Event5_NAC",
         "eventTemplateId": "EventTemplate_S37_SoloSeriesCup",
         "countdownBeginTime": "2025-10-12T21:00:00Z",
         "beginTime": "2025-10-12T23:00:00Z",
         "endTime": "2025-10-13T02:00:00Z",
         "round": 5,
         "payoutDelay": 32,
         "isTBD": false,
         "visibility": "public",
         "additionalRequirements": [
            "eula:s37_soloseries_rules",
            "adps:g-a81a33a3b9a7",
            "mfa",
            [
               "currentRanking:ranked-br:6",
               "currentRanking:ranked-zb:6",
               "currentRanking:ranked_blastberry_build:6",
               "currentRanking:ranked_blastberry_nobuild:6"
            ]
         ],
         "teammateEligibility": "all",
         "blackoutPeriods": [],
         "scoreLocations": [
            {
               "leaderboardDefId": "S37_SoloSeriesCup_DefaultLeaderboardDef",
               "isMainWindowLeaderboard": true
            },
            {
               "leaderboardDefId": "S37_SoloSeriesCup_SeriesLeaderboardDef",
               "isMainWindowLeaderboard": false
            }
         ],
         "canLiveSpectate": false,
         "requireAllTokens": [
            "S37_CashCup_Qualified"
         ],
         "requireAnyTokens": [],
         "requireNoneTokensCaller": [
            "EpicAccountPrizingRestriction_v2",
            "Permanent_Tournament_Ban"
         ],
         "requireAllTokensCaller": [],
         "requireAnyTokensCaller": [],
         "regionMappings": {},
         "metadata": {
            "asyncPayoutsExclusiveLeaderboardDefs": [
               "S37_SoloSeriesCup_SeriesLeaderboardDef"
            ],
            "RoundType": "Qualifiers",
            "ServerReplays": true
         }
      },
      {
         "eventWindowId": "S37_SoloSeriesCup_Event6_NAC",
         "eventTemplateId": "EventTemplate_S37_SoloSeriesCup",
         "countdownBeginTime": "2025-10-19T21:00:00Z",
         "beginTime": "2025-10-19T23:00:00Z",
         "endTime": "2025-10-20T02:00:00Z",
         "round": 6,
         "payoutDelay": 32,
         "isTBD": false,
         "visibility": "public",
         "additionalRequirements": [
            "eula:s37_soloseries_rules",
            "adps:g-a81a33a3b9a7",
            "mfa",
            [
               "currentRanking:ranked-br:6",
               "currentRanking:ranked-zb:6",
               "currentRanking:ranked_blastberry_build:6",
               "currentRanking:ranked_blastberry_nobuild:6"
            ]
         ],
         "teammateEligibility": "all",
         "blackoutPeriods": [],
         "scoreLocations": [
            {
               "leaderboardDefId": "S37_SoloSeriesCup_DefaultLeaderboardDef",
               "isMainWindowLeaderboard": true
            },
            {
               "leaderboardDefId": "S37_SoloSeriesCup_SeriesLeaderboardDef",
               "isMainWindowLeaderboard": false
            }
         ],
         "canLiveSpectate": false,
         "requireAllTokens": [
            "S37_CashCup_Qualified"
         ],
         "requireAnyTokens": [],
         "requireNoneTokensCaller": [
            "EpicAccountPrizingRestriction_v2",
            "Permanent_Tournament_Ban"
         ],
         "requireAllTokensCaller": [],
         "requireAnyTokensCaller": [],
         "regionMappings": {},
         "metadata": {
            "asyncPayoutsExclusiveLeaderboardDefs": [
               "S37_SoloSeriesCup_SeriesLeaderboardDef"
            ],
            "RoundType": "Qualifiers",
            "ServerReplays": true
         }
      },
      {
         "eventWindowId": "S37_SoloSeriesCup_Final_NAC",
         "eventTemplateId": "EventTemplate_S37_SoloSeriesCupFinal",
         "countdownBeginTime": "2025-10-26T21:00:00Z",
         "beginTime": "2025-10-26T23:00:00Z",
         "endTime": "2025-10-27T02:00:00Z",
         "round": 7,
         "payoutDelay": 32,
         "isTBD": false,
         "visibility": "public",
         "additionalRequirements": [
            "eula:s37_soloseries_rules",
            "adps:g-a81a33a3b9a7",
            "mfa"
         ],
         "teammateEligibility": "all",
         "blackoutPeriods": [],
         "scoreLocations": [
            {
               "leaderboardDefId": "S37_SoloSeriesCupFinal_DefaultLeaderboardDef",
               "isMainWindowLeaderboard": true
            }
         ],
         "canLiveSpectate": false,
         "requireAllTokens": [
            "S37_SoloSeries_Final_NAC"
         ],
         "requireAnyTokens": [],
         "requireNoneTokensCaller": [
            "EpicAccountPrizingRestriction_v2",
            "Permanent_Tournament_Ban"
         ],
         "requireAllTokensCaller": [],
         "requireAnyTokensCaller": [],
         "regionMappings": {},
         "metadata": {
            "RoundType": "Qualifiers",
            "ScheduledMatchmakingInitialDelaySeconds": 600,
            "ScheduledMatchmakingMatchDelaySeconds": 1920,
            "ServerReplays": true
         }
      }
   ],
   "link": {
      "type": "br:tournament",
      "code": "tournament_epicgames_s37_soloseriescup_nac"
   }
}