[
   {
      "scoringType": "value",
      "ranks": [
         {
            "threshold": 50,
            "payouts": [
               {
                  "rewardType": "game",
                  "rewardMode": "standard",
                  "value": "AthenaGlider:umbrella_rankedhalt",
                  "quantity": 1,
                  "notifiesPlayer": false
               }
            ]
         }
      ]
   },
   {
      "scoringType": "rank",
      "ranks": [
         {
            "threshold": 20,
            "payouts": [
               {
                  "rewardType": "game",
                  "rewardMode": "standard",
                  "value": "AthenaCharacter:character_rankedtrooper_noble",
                  "quantity": 1,
                  "notifiesPlayer": false
               }
            ]
         }
      ]
   }
]