[
   {
      "scoringType": "value",
      "ranks": [
         {
            "threshold": 1,
            "payouts": [
               {
                  "rewardType": "token",
                  "rewardMode": "standard",
                  "value": "S38_ReloadQuickCup_Event1Group3Round2_ME",
                  "quantity": 1,
                  "notifiesPlayer": false
               }
            ]
         },
         {
            "threshold": 10,
            "payouts": [
               {
                  "rewardType": "token",
                  "rewardMode": "standard",
                  "value": "S38_ReloadQuickCup_Event1Group2Round2_ME",
                  "quantity": 1,
                  "notifiesPlayer": false
               }
            ]
         },
         {
            "threshold": 15,
            "payouts": [
               {
                  "rewardType": "token",
                  "rewardMode": "standard",
                  "value": "S38_ReloadQuickCup_Event1Group1Round2_ME",
                  "quantity": 1,
                  "notifiesPlayer": false
               }
            ]
         }
      ]
   }
]